{"总登记号": "catalogNumber", "分类号": "otherCatalogNumbers", "入库批次": "batchNumber", "资源类型": "type", "保管位置": "preservedLocation", "标本来源": "fundedBy", "标签复份": "duplicatesOfLabel", "标签标题": "labelTitle", "保存方式": "preparations", "中文名": "chineseName", "中药拉丁名": "medicineScientificName", "采集人": "recordedBy", "采集号": "recordNumber", "采集日期": "eventDate", "纬度": "decimalLatitude", "经度": "decimalLongitude", "海拔": "minimumElevationInMeters", "采集地国": "country", "采集地省": "province", "采集地市": "prefecture", "采集地县": "county", "小地名": "locality", "生境": "habitat", "数量": "individualCount", "单位": "individualCountType", "基原中文科名": "familyChineseName", "基原拉丁科名": "family", "基原中文名": "vernacularName", "基原学名": "scientificName", "鉴定人": "identifiedBy", "鉴定日期": "dateIdentified", "习性": "lifeForm", "性别": "sex", "外形尺寸": "sampleSizeValue", "藏品描述": "materialEntityRemarks", "加工方法": "medicinePreparations", "化学成分": "chemistry", "功效": "efficacy", "药用部位": "organismRemarks", "出土地及年代": "locationRemarks", "保护级别": "protectedStatusOfChina", "备注": "occurrenceRemarks"}